pycounts_rn/__init__.py
pycounts_rn/plotting.py
pycounts_rn/pycounts_rn.py
pycounts_rn-0.1.0.dist-info/LICENSE
pycounts_rn-0.1.0.dist-info/WHEEL
pycounts_rn-0.1.0.dist-info/METADATA
pycounts_rn-0.1.0.dist-info/RECORD
